ensemble/AdaBoost.py
ensemble/GradientBoostingClassifier.py
ensemble/GradientBoostingRegressor.py
ensemble/RandomForestClassifier.py
ensemble/RandomForestRegressor.py
ensemble/StackingClassifier.py
ensemble/VotingClassifier.py
ensemble/__init__.py
metrics/Accuracy.py
metrics/BaseMetric.py
metrics/ConfusionMatrix.py
metrics/F1Score.py
metrics/MeanAbsoluteError.py
metrics/MeanSquaredError.py
metrics/Precision.py
metrics/RSquared.py
metrics/Recall.py
metrics/RootMeanSquaredError.py
metrics/__init__.py
model_selection/GridSearchCV.py
model_selection/KFold.py
model_selection/ParameterGrid.py
model_selection/__init__.py
model_selection/train_test_split.py
neural_networks/MLP.py
neural_networks/MLPRegressor.py
neural_networks/Perceptron.py
neural_networks/__init__.py
preprocessing/LabelEncoder.py
preprocessing/MinMaxScaler.py
preprocessing/OneHotEncoder.py
preprocessing/SimpleImputer.py
preprocessing/StandardScaler.py
preprocessing/__init__.py
supervised_learning/BaseEstimator.py
supervised_learning/__init__.py
supervised_learning/classification/DecisionTreeClassifier.py
supervised_learning/classification/KNNClassifier.py
supervised_learning/classification/LogisticRegression.py
supervised_learning/classification/NaiveBayes.py
supervised_learning/classification/SVM.py
supervised_learning/classification/__init__.py
supervised_learning/regression/DecisionTreeRegressor.py
supervised_learning/regression/LinearRegression.py
supervised_learning/regression/__init__.py
utilities/__init__.py
utilities/data_manipulation.py
utilities/file_handling.py
cc_mini_scikit_learn-0.1.4.dist-info/METADATA
cc_mini_scikit_learn-0.1.4.dist-info/WHEEL
cc_mini_scikit_learn-0.1.4.dist-info/top_level.txt
cc_mini_scikit_learn-0.1.4.dist-info/RECORD
